Metadata-Version: 1.1
Name: clang-5
Version: 5.0
Summary: libclang python bindings
Home-page: http://clang.llvm.org/
Author: LLVM team
Author-email: UNKNOWN
License: License :: OSI Approved :: University of Illinois/NCSA Open Source License
Download-URL: http://llvm.org/releases/download.html
Keywords: llvm,clang,libclang
Platform: UNKNOWN
Classifier: Intended Audience :: Developers
Classifier: License :: OSI Approved :: University of Illinois/NCSA Open Source License
Classifier: Development Status :: 5 - Production/Stable
Classifier: Topic :: Software Development :: Compilers
Classifier: Programming Language :: Python :: 2.7
Classifier: Programming Language :: Python :: 3.4
